elia_chat/__init__.py
elia_chat/__main__.py
elia_chat/app.py
elia_chat/chats_manager.py
elia_chat/config.py
elia_chat/constants.py
elia_chat/elia.scss
elia_chat/launch_args.py
elia_chat/locations.py
elia_chat/models.py
elia_chat/runtime_config.py
elia_chat/themes.py
elia_chat/time_display.py
elia_chat/database/__init__.py
elia_chat/database/converters.py
elia_chat/database/database.py
elia_chat/database/import_chatgpt.py
elia_chat/database/models.py
elia_chat/screens/chat_details.py
elia_chat/screens/chat_screen.py
elia_chat/screens/help_screen.py
elia_chat/screens/home_screen.py
elia_chat/screens/rename_chat_screen.py
elia_chat/widgets/agent_is_typing.py
elia_chat/widgets/app_header.py
elia_chat/widgets/chat.py
elia_chat/widgets/chat_header.py
elia_chat/widgets/chat_list.py
elia_chat/widgets/chat_options.py
elia_chat/widgets/chatbox.py
elia_chat/widgets/prompt_input.py
elia_chat/widgets/token_analysis.py
elia_chat/widgets/welcome.py
elia_chat-1.10.0.dist-info/METADATA
elia_chat-1.10.0.dist-info/WHEEL
elia_chat-1.10.0.dist-info/entry_points.txt
elia_chat-1.10.0.dist-info/licenses/LICENSE
elia_chat-1.10.0.dist-info/RECORD
