Metadata-Version: 2.3
Name: elia_chat
Version: 1.10.0
Summary: A powerful terminal user interface for interacting with large language models.
Author-email: Darren Burns <darrenb900@gmail.com>
License-File: LICENSE
Requires-Python: >=3.11
Requires-Dist: aiosqlite>=0.20.0
Requires-Dist: click-default-group>=1.2.4
Requires-Dist: click>=8.1.6
Requires-Dist: google-generativeai>=0.5.3
Requires-Dist: greenlet>=3.0.3
Requires-Dist: humanize>=4.6.0
Requires-Dist: litellm>=1.37.19
Requires-Dist: pydantic>=2.9.0
Requires-Dist: pyperclip>=1.8.2
Requires-Dist: sqlmodel>=0.0.9
Requires-Dist: textual[syntax]==0.79.1
Requires-Dist: xdg-base-dirs>=6.0.1
